MANIFEST.in
README.md
setup.py
django_markdown_shortcodes.egg-info/PKG-INFO
django_markdown_shortcodes.egg-info/SOURCES.txt
django_markdown_shortcodes.egg-info/dependency_links.txt
django_markdown_shortcodes.egg-info/requires.txt
django_markdown_shortcodes.egg-info/top_level.txt
markdown_shortcodes/__init__.py
markdown_shortcodes/templates/shortcodes/vimeo.html
markdown_shortcodes/templatetags/__init__.py
markdown_shortcodes/templatetags/shortcodes.py