Metadata-Version: 1.1
Name: django-markdown-shortcodes
Version: 1.2
Summary: Utility adding WordPress-like shortcodes for Markdown authoring in Django.
Home-page: https://github.com/defbyte/django-markdown-shortcodes
Author: Chris Davis
Author-email: defbyte@gmail.com
License: BSD License
Platform: UNKNOWN
Classifier: Development Status :: 4 - Beta
Classifier: Environment :: Web Environment
Classifier: Framework :: Django
Classifier: Intended Audience :: Developers
Classifier: License :: OSI Approved :: BSD License
Classifier: Operating System :: OS Independent
Classifier: Programming Language :: Python
